animalib/__init__.py
animalib/animalib.py
animalib-0.0.9.dist-info/LICENSE.md
animalib-0.0.9.dist-info/METADATA
animalib-0.0.9.dist-info/WHEEL
animalib-0.0.9.dist-info/top_level.txt
animalib-0.0.9.dist-info/RECORD
