Metadata-Version: 2.1
Name: animalib
Version: 0.0.9
Summary: A small library to handle animations in PyGame
Home-page: https://github.com/SushiCannibale/AnimaLib
Author: _SushiCannibale_
Author-email: sushi.cannibale@gmail.com
License: UNKNOWN
Project-URL: Bug Tracker, https://github.com/SushiCannibale/AnimaLib/issues
Platform: UNKNOWN
Classifier: Programming Language :: Python :: 3
Classifier: License :: OSI Approved :: MIT License
Classifier: Operating System :: OS Independent
Requires-Python: >=3.6
License-File: LICENSE.md
